ed_infrastructure/__init__.py
ed_infrastructure/common/__init__.py
ed_infrastructure/common/generic.py
ed_infrastructure/common/logging.py
ed_infrastructure/documentation/__init__.py
ed_infrastructure/documentation/api/__init__.py
ed_infrastructure/documentation/api/endpoint_client.py
ed_infrastructure/documentation/message_queue/__init__.py
ed_infrastructure/documentation/message_queue/rabbitmq/__init__.py
ed_infrastructure/documentation/message_queue/rabbitmq/rabbitmq_multiple_queue_producers.py
ed_infrastructure/documentation/message_queue/rabbitmq/rabbitmq_producer.py
ed_infrastructure/persistence/__init__.py
ed_infrastructure/persistence/helpers.py
ed_infrastructure/persistence/sqlalchemy/__init__.py
ed_infrastructure/persistence/sqlalchemy/db_engine.py
ed_infrastructure/persistence/sqlalchemy/db_session.py
ed_infrastructure/persistence/sqlalchemy/demo.py
ed_infrastructure/persistence/sqlalchemy/run_seed.py
ed_infrastructure/persistence/sqlalchemy/seed_consumers.py
ed_infrastructure/persistence/sqlalchemy/unit_of_work.py
ed_infrastructure/persistence/sqlalchemy/models/__init__.py
ed_infrastructure/persistence/sqlalchemy/models/all_models.py
ed_infrastructure/persistence/sqlalchemy/models/base_model.py
ed_infrastructure/persistence/sqlalchemy/repositories/__init__.py
ed_infrastructure/persistence/sqlalchemy/repositories/admin_repository.py
ed_infrastructure/persistence/sqlalchemy/repositories/api_key_repository.py
ed_infrastructure/persistence/sqlalchemy/repositories/auth_user_repository.py
ed_infrastructure/persistence/sqlalchemy/repositories/bill_repository.py
ed_infrastructure/persistence/sqlalchemy/repositories/business_repository.py
ed_infrastructure/persistence/sqlalchemy/repositories/car_repository.py
ed_infrastructure/persistence/sqlalchemy/repositories/consumer_repository.py
ed_infrastructure/persistence/sqlalchemy/repositories/delivery_job_repository.py
ed_infrastructure/persistence/sqlalchemy/repositories/driver_repository.py
ed_infrastructure-0.4.6.dist-info/licenses/LICENSE
ed_infrastructure-0.4.6.dist-info/METADATA
ed_infrastructure-0.4.6.dist-info/WHEEL
ed_infrastructure-0.4.6.dist-info/top_level.txt
ed_infrastructure-0.4.6.dist-info/RECORD
